Workbook

Sheet Assumptions
A1: HydroWarm — Financial Model
A2: Assumptions
A3: Blue = input, edit freely. Black = formula, don't overwrite. Green (on other tabs) = link from this sheet. Grey italic notes = estimate, not from the source handover — validate before relying on it.
A5: 1. Product economics
A6: Product | B6: Retail price (€) | C6: COGS – China (€) | D6: COGS – EU (€) | E6: Wholesale price (€) | F6: Notes
A7: Comfort | B7: 36 | C7: 13 | E7: =B7*(1-$B$17) | F7: Retail: midpoint of €34–39 (handover). COGS: midpoint of €11–15 China-track (handover).
A8: Charge Single | B8: 59 | C8: 18 | E8: =B8*(1-$B$17) | F8: Retail locked (handover). COGS: ESTIMATE — not yet quoted (Charge Factory Spec v1.0); placeholder scaled up from Comfort.
A9: Charge Double | B9: 69 | C9: 21 | E9: =B9*(1-$B$17) | F9: Retail locked (handover). COGS: ESTIMATE — not yet quoted; placeholder scaled from Charge Single.
A10: Boot Standard | B10: 39 | C10: 9.5 | D10: 24 | E10: =B10*(1-$B$17) | F10: Retail + both COGS tracks from handover (China €7–12 mid; EU €20–28 mid).
A11: Boot Pro | B11: 54 | C11: 11 | D11: 26 | E11: =B11*(1-$B$17) | F11: Retail locked (handover). COGS: ESTIMATE — Standard + side-zipper premium; not itemised in source.
A12: Neck Standard | B12: 34 | C12: 8 | D12: 18 | E12: =B12*(1-$B$17) | F12: Retail locked (handover). COGS: ESTIMATE — simpler build than Boot (no grid sole); not itemised in source.
A13: Cape | B13: 59 | C13: 13 | D13: 26 | E13: =B13*(1-$B$17) | F13: Retail locked (handover). COGS: ESTIMATE — larger surface area than Neck; not itemised in source.
A15: 2. Channel cost assumptions
A16: Parameter | B16: Value | F16: Notes
A17: Partner wholesale discount off retail | B17: 0.65 | F17: ESTIMATE — mass-retail wholesale discount typical of Action / B&M / Lidl tier. Not itemised in source; adjust once partners quote real terms.
A18: Direct payment processing fee (% of revenue) | B18: 0.03 | F18: ESTIMATE — typical EU card/marketplace processing (Stripe, Adyen, Bol.com / Amazon referral fee blend).
A19: Direct fulfillment cost per unit (€) | B19: 2 | F19: ESTIMATE — pick/pack/ship within NL/EU.
A20: Direct marketing spend (% of revenue) | B20: 0.05 | F20: ESTIMATE — paid acquisition + content, direct channel only. Partners market their own shelf space.
A21: Partner distributor commission (% of wholesale revenue) | B21: 0.08 | F21: ESTIMATE — ConnaBride-style distribution commission.
A22: Partner logistics cost per unit (€) | B22: 1.5 | F22: ESTIMATE — bulk pallet shipping to distributor/retailer DC, cheaper per-unit than direct-to-consumer.
A24: 3. Scenario volumes
A25: Parameter | B25: Value | F25: Notes
A26: Boot Standard units — Year 2 scenario | B26: 20000 | F26: Source: handover Section 10 ("20,000 boots").
A27: Neck Standard units — Year 2 scenario | B27: 20000 | F27: Source: handover Section 10 ("20,000 necks").
A28: Comfort units — Year 1, direct only | B28: 1000 | F28: Source: handover Section 10.
A29: Comfort units — break-even | B29: 228 | F29: Source: handover Section 10.
A30: Mixed strategy — direct channel share | B30: 0.5 | F30: Source: handover — recommended 50/50 direct/partner split for Year 2.

Sheet Direct Channel
A1: HydroWarm — Direct Channel
A2: Revenue and profit sold direct-to-consumer (Bol.com, Amazon, own site) at full retail price.
A4: Line item | B4: Units | C4: Retail price /unit (€) | D4: COGS /unit – China (€) | E4: Revenue (€) | F4: COGS (€) | G4: Payment fee (€) | H4: Fulfillment (€) | I4: Marketing (€) | J4: Net profit (€) | K4: Net margin (%)
A5: Boot Standard — Year 2 | B5: =Assumptions!$B$26 | C5: =Assumptions!$B$10 | D5: =Assumptions!$C$10 | E5: =B5*C5 | F5: =B5*D5 | G5: =E5*Assumptions!$B$18 | H5: =B5*Assumptions!$B$19 | I5: =E5*Assumptions!$B$20 | J5: =E5-SUM(F5:I5) | K5: =IFERROR(J5/E5,0)
A6: Neck Standard — Year 2 | B6: =Assumptions!$B$27 | C6: =Assumptions!$B$12 | D6: =Assumptions!$C$12 | E6: =B6*C6 | F6: =B6*D6 | G6: =E6*Assumptions!$B$18 | H6: =B6*Assumptions!$B$19 | I6: =E6*Assumptions!$B$20 | J6: =E6-SUM(F6:I6) | K6: =IFERROR(J6/E6,0)
A7: Subtotal — Year 2 (Boot + Neck, 40,000 units) | B7: =SUM(B5:B6) | E7: =SUM(E5:E6) | F7: =SUM(F5:F6) | G7: =SUM(G5:G6) | H7: =SUM(H5:H6) | I7: =SUM(I5:I6) | J7: =SUM(J5:J6) | K7: =IFERROR(J7/E7,0)
A9: Comfort milestones (direct only)
A10: Comfort — Year 1 (direct only) | B10: =Assumptions!$B$28 | C10: =Assumptions!$B$7 | D10: =Assumptions!$C$7 | E10: =B10*C10 | F10: =B10*D10 | G10: =E10*Assumptions!$B$18 | H10: =B10*Assumptions!$B$19 | I10: =E10*Assumptions!$B$20 | J10: =E10-SUM(F10:I10) | K10: =IFERROR(J10/E10,0)
A11: Comfort — break-even | B11: =Assumptions!$B$29 | C11: =Assumptions!$B$7 | D11: =Assumptions!$C$7 | E11: =B11*C11 | F11: =B11*D11 | G11: =E11*Assumptions!$B$18 | H11: =B11*Assumptions!$B$19 | I11: =E11*Assumptions!$B$20 | J11: =E11-SUM(F11:I11) | K11: =IFERROR(J11/E11,0)

Sheet Partner Channels
A1: HydroWarm — Partner Channels
A2: Revenue and profit sold wholesale through retail partners (Action, B&M, Lidl via ConnaBride, Decathlon).
A4: Line item | B4: Units | C4: Wholesale price /unit (€) | D4: COGS /unit – China (€) | E4: Revenue (€) | F4: COGS (€) | G4: Distributor commission (€) | H4: Logistics (€) | I4: Total cost (€) | J4: Net profit (€) | K4: Net margin (%)
A5: Boot Standard — Year 2 | B5: =Assumptions!$B$26 | C5: =Assumptions!$E$10 | D5: =Assumptions!$C$10 | E5: =B5*C5 | F5: =B5*D5 | G5: =E5*Assumptions!$B$21 | H5: =B5*Assumptions!$B$22 | I5: =SUM(F5:H5) | J5: =E5-I5 | K5: =IFERROR(J5/E5,0)
A6: Neck Standard — Year 2 | B6: =Assumptions!$B$27 | C6: =Assumptions!$E$12 | D6: =Assumptions!$C$12 | E6: =B6*C6 | F6: =B6*D6 | G6: =E6*Assumptions!$B$21 | H6: =B6*Assumptions!$B$22 | I6: =SUM(F6:H6) | J6: =E6-I6 | K6: =IFERROR(J6/E6,0)
A7: Subtotal — Year 2 (Boot + Neck, 40,000 units) | B7: =SUM(B5:B6) | E7: =SUM(E5:E6) | F7: =SUM(F5:F6) | G7: =SUM(G5:G6) | H7: =SUM(H5:H6) | I7: =SUM(I5:I6) | J7: =SUM(J5:J6) | K7: =IFERROR(J7/E7,0)

Sheet Scenario Comparison
A1: HydroWarm — Scenario Comparison
A2: Model output (from Assumptions) next to the figures stated in the July 2026 project handover, for a reality check while real channel costs are still being quoted.
A5: Scenario | B5: Units | C5: Revenue (€) | D5: Net profit (€) | E5: Net margin (%) | F5: Handover figures (July 2026) — Revenue / Profit / Margin | I5: Notes
F6: Revenue (€) | G6: Profit (€) | H6: Margin (%)
A7: Break-even — Comfort | B7: ='Direct Channel'!$B$11 | C7: ='Direct Channel'!$E$11 | D7: ='Direct Channel'!$J$11 | E7: =IFERROR(D7/C7,0) | F7: 8200 | G7: 0 | H7: 0 | I7: Direct channel only. Handover margin shown as 0% at this volume by definition (break-even).
A8: Year 1 — Comfort, direct only | B8: ='Direct Channel'!$B$10 | C8: ='Direct Channel'!$E$10 | D8: ='Direct Channel'!$J$10 | E8: =IFERROR(D8/C8,0) | F8: 36000 | G8: 21600 | H8: 0.6 | I8: First full year, direct channels only.
A9: Year 2 — All Direct (40,000 units) | B9: ='Direct Channel'!$B$7 | C9: ='Direct Channel'!$E$7 | D9: ='Direct Channel'!$J$7 | E9: =IFERROR(D9/C9,0) | F9: 1460000 | G9: 990000 | H9: 0.68 | I9: 20,000 Boot + 20,000 Neck, 100% direct-to-consumer.
A10: Year 2 — All Partners (40,000 units) | B10: ='Partner Channels'!$B$7 | C10: ='Partner Channels'!$E$7 | D10: ='Partner Channels'!$J$7 | E10: =IFERROR(D10/C10,0) | F10: 380000 | G10: 50000 | H10: 0.13 | I10: Same volume, 100% wholesale through retail partners.
A11: Year 2 — Mixed 50/50 (recommended) | B11: ='Direct Channel'!$B$7 | C11: ='Direct Channel'!$E$7*Assumptions!$B$30+'Partner Channels'!$E$7*(1-Assumptions!$B$30) | D11: ='Direct Channel'!$J$7*Assumptions!$B$30+'Partner Channels'!$J$7*(1-Assumptions!$B$30) | E11: =IFERROR(D11/C11,0) | F11: 920000 | G11: 520000 | H11: 0.57 | I11: Same 40,000 units, split by the direct-channel share set in Assumptions (default 50%).
A13: The July 2026 handover gives aggregate outcomes only, not the underlying per-channel cost breakdown — so the model columns (C–E) will not tie exactly to the handover columns (F–H) until the Assumptions tab is updated with real factory and distribution quotes. Treat columns F–H as the reality check, and tune Assumptions until C–E converge on them.

Sheet Dashboard
B2: HydroWarm — Financial Model Dashboard
B3: Warm the person. Not the room. · Model reference: July 2026 handover, reconstructed with editable assumptions.
B5: RECOMMENDED — YEAR 2 REVENUE | D5: RECOMMENDED — YEAR 2 NET PROFIT | F5: RECOMMENDED — NET MARGIN
B6: ='Scenario Comparison'!$C$11 | D6: ='Scenario Comparison'!$D$11 | F6: ='Scenario Comparison'!$E$11
A10: Year 2 · 40,000 units — by channel strategy
B11: Scenario | C11: Revenue (€) | D11: Net profit (€) | E11: Net margin (%)
B12: ='Scenario Comparison'!$A$9 | C12: ='Scenario Comparison'!$C$9 | D12: ='Scenario Comparison'!$D$9 | E12: ='Scenario Comparison'!$E$9
B13: ='Scenario Comparison'!$A$10 | C13: ='Scenario Comparison'!$C$10 | D13: ='Scenario Comparison'!$D$10 | E13: ='Scenario Comparison'!$E$10
B14: ='Scenario Comparison'!$A$11 | C14: ='Scenario Comparison'!$C$11 | D14: ='Scenario Comparison'!$D$11 | E14: ='Scenario Comparison'!$E$11
A36: Early milestones (Comfort, direct only)
B37: Milestone | C37: Units | D37: Revenue (€) | E37: Net profit (€)
B38: ='Scenario Comparison'!$A$7 | C38: ='Scenario Comparison'!$B$7 | D38: ='Scenario Comparison'!$C$7 | E38: ='Scenario Comparison'!$D$7
B39: ='Scenario Comparison'!$A$8 | C39: ='Scenario Comparison'!$B$8 | D39: ='Scenario Comparison'!$C$8 | E39: ='Scenario Comparison'!$D$8
B42: Recommended strategy: direct channels for margin, retail partners for volume and brand exposure. The 50/50 mix trades some revenue for a margin partners alone can't deliver — tune the direct-channel share in Assumptions (Section 3) to explore other splits.
